{
    "comma": {
        "branch": "master",
        "description": null,
        "homepage": null,
        "owner": "SuperSandro2000",
        "repo": "comma",
        "rev": "28f94a11114893506ea2c5c5bdbc1dae1d1d8159",
        "sha256": "05157wn3f1whq6krcijhipkjw5zjml5h4xbf06ibd77kc57lqw8z",
        "type": "tarball",
        "url": "https://github.com/SuperSandro2000/comma/archive/28f94a11114893506ea2c5c5bdbc1dae1d1d8159.tar.gz",
        "url_template": "https://github.com/<owner>/<repo>/archive/<rev>.tar.gz"
    },
    "easy-hls-nix": {
        "branch": "main",
        "description": "Easy Haskell Language Server tooling with Nix!",
        "homepage": null,
        "owner": "jkachmar",
        "repo": "easy-hls-nix",
        "rev": "9d64543a015563942c954b89addc1108800ed134",
        "sha256": "1szq3g34dv22fqzil549mvpdd1865s64vqnfxj0l2aw9ha32jxyz",
        "type": "tarball",
        "url": "https://github.com/jkachmar/easy-hls-nix/archive/9d64543a015563942c954b89addc1108800ed134.tar.gz",
        "url_template": "https://github.com/<owner>/<repo>/archive/<rev>.tar.gz"
    },
    "neovim-nightly-overlay": {
        "branch": "master",
        "description": "[maintainer=@mjlbach] ",
        "homepage": "",
        "owner": "nix-community",
        "repo": "neovim-nightly-overlay",
        "rev": "96225ac9d5895eb939d1a15db14597e3cd16d812",
        "sha256": "0klm3dc6il94y3h16z9c13prvs12j5ahbwlk3qjmy5342z0fyjr2",
        "type": "tarball",
        "url": "https://github.com/nix-community/neovim-nightly-overlay/archive/96225ac9d5895eb939d1a15db14597e3cd16d812.tar.gz",
        "url_template": "https://github.com/<owner>/<repo>/archive/<rev>.tar.gz"
    },
    "niv": {
        "branch": "master",
        "description": "Easy dependency management for Nix projects",
        "homepage": "https://github.com/nmattia/niv",
        "owner": "nmattia",
        "repo": "niv",
        "rev": "e0ca65c81a2d7a4d82a189f1e23a48d59ad42070",
        "sha256": "1pq9nh1d8nn3xvbdny8fafzw87mj7gsmp6pxkdl65w2g18rmcmzx",
        "type": "tarball",
        "url": "https://github.com/nmattia/niv/archive/e0ca65c81a2d7a4d82a189f1e23a48d59ad42070.tar.gz",
        "url_template": "https://github.com/<owner>/<repo>/archive/<rev>.tar.gz"
    },
    "nixpkgs": {
        "branch": "nixos-21.05",
        "description": "Nix Packages collection",
        "homepage": "",
        "owner": "NixOS",
        "repo": "nixpkgs",
        "rev": "71326cd12ddfa0fac40fdb451fcba7dad763c56e",
        "sha256": "1939fwll9xwm7mf5crz7gfvz41c8gqd8wg7fy2v6m71viiq8lrda",
        "type": "tarball",
        "url": "https://github.com/NixOS/nixpkgs/archive/71326cd12ddfa0fac40fdb451fcba7dad763c56e.tar.gz",
        "url_template": "https://github.com/<owner>/<repo>/archive/<rev>.tar.gz"
    },
    "nixpkgs-unstable": {
        "branch": "nixpkgs-unstable",
        "description": "Nix Packages collection",
        "homepage": "",
        "owner": "NixOS",
        "repo": "nixpkgs",
        "rev": "db6e089456cdddcd7e2c1d8dac37a505c797e8fa",
        "sha256": "02yk20i9n5nhn6zgll3af7kp3q5flgrpg1h5vcqfdqcck8iikx4b",
        "type": "tarball",
        "url": "https://github.com/NixOS/nixpkgs/archive/db6e089456cdddcd7e2c1d8dac37a505c797e8fa.tar.gz",
        "url_template": "https://github.com/<owner>/<repo>/archive/<rev>.tar.gz"
    },
    "nixpkgs-wayland": {
        "branch": "master",
        "description": "Automated, pre-built packages for Wayland (sway/wlroots) tools for NixOS.",
        "homepage": "",
        "owner": "colemickens",
        "repo": "nixpkgs-wayland",
        "rev": "03f164c2a5344768c8186989c30045b7c8c7ebf7",
        "sha256": "1925rl2fwx89v8wkvfi88m3kiddygjwjqydiqsz7c54dqi2smsi3",
        "type": "tarball",
        "url": "https://github.com/colemickens/nixpkgs-wayland/archive/03f164c2a5344768c8186989c30045b7c8c7ebf7.tar.gz",
        "url_template": "https://github.com/<owner>/<repo>/archive/<rev>.tar.gz"
    },
    "vim-bujo": {
        "branch": "master",
        "description": "A minimalist task manager for vim.",
        "homepage": "",
        "owner": "vuciv",
        "repo": "vim-bujo",
        "rev": "ae87612ccabd0460c6f71387b7b23515383d5468",
        "sha256": "17ca3pgy6fipk1s1f2dlxdmgcd2h761dk9qm6dy4cmhvvac69lnh",
        "type": "tarball",
        "url": "https://github.com/vuciv/vim-bujo/archive/ae87612ccabd0460c6f71387b7b23515383d5468.tar.gz",
        "url_template": "https://github.com/<owner>/<repo>/archive/<rev>.tar.gz"
    },
    "vim-silicon": {
        "branch": "master",
        "description": "Vim plugin for generating images of source code using https://github.com/Aloxaf/silicon",
        "homepage": "",
        "owner": "segeljakt",
        "repo": "vim-silicon",
        "rev": "4a93122ae2139a12e2a56f064d086c05160b6835",
        "sha256": "1q323d787a3rxycx0s5qhkfy18cic7jm80b5pzd1bzs31as8g47j",
        "type": "tarball",
        "url": "https://github.com/segeljakt/vim-silicon/archive/4a93122ae2139a12e2a56f064d086c05160b6835.tar.gz",
        "url_template": "https://github.com/<owner>/<repo>/archive/<rev>.tar.gz"
    }
}
